{
  "info": {
    "description": "data",
    "version": "1.0",
    "year": 2025,
    "contributor": "search engine",
    "source": "augmented",
    "license": {
      "name": "Creative Commons Attribution 4.0 International",
      "url": "https://creativecommons.org/licenses/by/4.0/"
    }
  },
  "images": [
    {
      "id": 5091469660,
      "width": 512,
      "height": 512,
      "file_name": "VegAnn_3320.png",
      "size": 607205,
      "format": "PNG",
      "url": "",
      "hash": "",
      "status": "success"
    }
  ],
  "annotations": [
    {
      "id": 4574158660,
      "image_id": 5091469660,
      "category_id": 6,
      "segmentation": [
        [
          135,
          209,
          511,
          209,
          511,
          452,
          135,
          452
        ]
      ],
      "area": 91368,
      "bbox": [
        135,
        209,
        376,
        243
      ]
    }
  ],
  "categories": [
    {
      "id": 6,
      "name": "Mix",
      "supercategory": "vegann"
    }
  ]
}