{
  "info": {
    "description": "data",
    "version": "1.0",
    "year": 2025,
    "contributor": "search engine",
    "source": "augmented",
    "license": {
      "name": "Creative Commons Attribution 4.0 International",
      "url": "https://creativecommons.org/licenses/by/4.0/"
    }
  },
  "images": [
    {
      "id": 6372454616,
      "width": 512,
      "height": 512,
      "file_name": "VegAnn_91.png",
      "size": 603754,
      "format": "PNG",
      "url": "",
      "hash": "",
      "status": "success"
    }
  ],
  "annotations": [
    {
      "id": 2514353616,
      "image_id": 6372454616,
      "category_id": 6,
      "segmentation": [
        [
          25,
          40,
          511,
          40,
          511,
          511,
          25,
          511
        ]
      ],
      "area": 228906,
      "bbox": [
        25,
        40,
        486,
        471
      ]
    }
  ],
  "categories": [
    {
      "id": 6,
      "name": "Mix",
      "supercategory": "vegann"
    }
  ]
}