{
  "info": {
    "description": "data",
    "version": "1.0",
    "year": 2025,
    "contributor": "search engine",
    "source": "augmented",
    "license": {
      "name": "Creative Commons Attribution 4.0 International",
      "url": "https://creativecommons.org/licenses/by/4.0/"
    }
  },
  "images": [
    {
      "id": 5022463635,
      "width": 512,
      "height": 512,
      "file_name": "VegAnn_1745.png",
      "size": 607609,
      "format": "PNG",
      "url": "",
      "hash": "",
      "status": "success"
    }
  ],
  "annotations": [
    {
      "id": 4850434635,
      "image_id": 5022463635,
      "category_id": 4,
      "segmentation": [
        [
          0,
          181,
          448,
          181,
          448,
          428,
          0,
          428
        ]
      ],
      "area": 110656,
      "bbox": [
        0,
        181,
        448,
        247
      ]
    }
  ],
  "categories": [
    {
      "id": 4,
      "name": "Wheat",
      "supercategory": "vegann"
    }
  ]
}